{
    "items": [
        {
            "id": 1,
            "name": "Dresser",
            "texture": "dresser",
            "pickupDist": 20,
            "actions": [
				{
					"type": "pickup",
					"item": 2,
					"remove": false
				}
			]
        },
        {
            "id": 2,
            "name": "Love Letter",
            "texture": "letter",
            "actions": [
                { 
                    "type": "read",
                    "text": "My Dearest Love..."
                }
            ]
        }
    ]
}